MarkDo-0.3.0.dist-info/entry_points.txt
MarkDo-0.3.0.dist-info/top_level.txt
MarkDo-0.3.0.dist-info/METADATA
MarkDo-0.3.0.dist-info/RECORD
MarkDo-0.3.0.dist-info/DESCRIPTION.rst
MarkDo-0.3.0.dist-info/WHEEL
MarkDo-0.3.0.dist-info/metadata.json
markdo/markdo.py
markdo/markdo
markdo/__init__.py
markdo/static/base.css
markdo/static/bower/jquery/jquery.min.map
markdo/static/bower/jquery/.bower.json
markdo/static/bower/jquery/jquery-migrate.js
markdo/static/bower/jquery/.gitignore
markdo/static/bower/jquery/bower.json
markdo/static/bower/jquery/component.json
markdo/static/bower/jquery/jquery.min.js
markdo/static/bower/jquery/jquery-migrate.min.js
markdo/static/bower/jquery/jquery.js
markdo/static/bower/jquery/README.md
markdo/static/bower/jquery/composer.json
markdo/static/bower/jquery/package.json
markdo/static/bower/font-awesome/_config.yml
markdo/static/bower/font-awesome/CONTRIBUTING.md
markdo/static/bower/font-awesome/.bower.json
markdo/static/bower/font-awesome/Gemfile
markdo/static/bower/font-awesome/.gitignore
markdo/static/bower/font-awesome/component.json
markdo/static/bower/font-awesome/Gemfile.lock
markdo/static/bower/font-awesome/README.md
markdo/static/bower/font-awesome/composer.json
markdo/static/bower/font-awesome/package.json
markdo/static/bower/font-awesome/css/font-awesome.css
markdo/static/bower/font-awesome/css/font-awesome.min.css
markdo/static/bower/font-awesome/fonts/fontawesome-webfont.eot
markdo/static/bower/font-awesome/fonts/fontawesome-webfont.woff
markdo/static/bower/font-awesome/fonts/FontAwesome.otf
markdo/static/bower/font-awesome/fonts/fontawesome-webfont.ttf
markdo/static/bower/font-awesome/fonts/fontawesome-webfont.svg
markdo/static/bower/codemirror/CONTRIBUTING.md
markdo/static/bower/codemirror/.bower.json
markdo/static/bower/codemirror/index.html
markdo/static/bower/codemirror/.gitignore
markdo/static/bower/codemirror/.travis.yml
markdo/static/bower/codemirror/LICENSE
markdo/static/bower/codemirror/README.md
markdo/static/bower/codemirror/.gitattributes
markdo/static/bower/codemirror/package.json
markdo/static/bower/codemirror/keymap/vim.js
markdo/static/bower/codemirror/keymap/emacs.js
