Metadata-Version: 2.0
Name: MarkDo
Version: 0.3.0
Summary: Markdown editor for Gnome
Home-page: http://nitipit.github.com/markdo/
Author: Nitipit Nontasuwan
Author-email: nitipit@gmail.com
License: MIT
Keywords: editor,markdown
Platform: linux
Platform: gnome
Requires-Dist: appkit (>=0.2.8)
